{
  "status": "ok",
  "extraction": {
    "client": {
      "name": "Aura Builders & Consultants",
      "address": "317, Luxuria Buissness Hub Dumas Road Vesu, Surat, Gujrat-395007",
      "phone": null,
      "gstin": null
    },
    "date": "2026-01-29",
    "ref_number": "25-26/IS/PI/219",
    "items": [
      {
        "product": "Football Goal Post Movable and Portable",
        "brand": null,
        "quantity": 1,
        "unit_price": 36960.0,
        "hsn_code": null
      },
      {
        "product": "Small Size 10‘X7’ Made of 3” Dia Pipe",
        "brand": null,
        "quantity": 1,
        "unit_price": 2800.0,
        "hsn_code": null
      },
      {
        "product": "Volleyball Pole Fix Type",
        "brand": null,
        "quantity": 1,
        "unit_price": 15120.0,
        "hsn_code": null
      },
      {
        "product": "Volleyball Net Garware Tournament",
        "brand": null,
        "quantity": 1,
        "unit_price": 3187.0,
        "hsn_code": null
      }
    ],
    "source_file": "_004401dc90ec_97c899a0_c759cce0_bajajsports.com__1.html",
    "doc_type": "invoice"
  },
  "fixes": [],
  "flags": []
}