{
  "status": "ok",
  "extraction": {
    "client": {
      "name": "HR Enterprises",
      "address": "Pani Khaiti, Lahapara, Guwahati, Kamrup Metropolition, Assam-781026",
      "phone": null,
      "gstin": null
    },
    "date": "2026-01-12",
    "ref_number": "25-26/IS/PI/202",
    "items": [
      {
        "product": "Table Tennis Table Stag Champion icon",
        "brand": null,
        "quantity": 4,
        "unit_price": 32625.0,
        "hsn_code": "95069990"
      },
      {
        "product": "Ship Rollon Packing Wooden Carret",
        "brand": null,
        "quantity": 4,
        "unit_price": 1429.0,
        "hsn_code": "996719"
      }
    ],
    "source_file": "_032201dc83a4_3899c8f0_a9cd5ad0_bajajsports.com__1.html",
    "doc_type": "invoice"
  },
  "fixes": [],
  "flags": []
}